pon/__init__.py
pon/constants.py
pon/setting.py
pon/amqp/__init__.py
pon/amqp/pool/__init__.py
pon/amqp/pool/connection.py
pon/amqp/pool/producer.py
pon/cli/__init__.py
pon/cli/main.py
pon/cli/patch.py
pon/cli/run.py
pon/cli/shell.py
pon/core/__init__.py
pon/env/__init__.py
pon/env/parsers.py
pon/events/__init__.py
pon/events/hints.py
pon/events/message.py
pon/events/register.py
pon/standalone/__init__.py
pon/standalone/events/__init__.py
pon/standalone/rpc/__init__.py
pon/timer/__init__.py
pon/timer/register.py
pon/web/__init__.py
pon/web/entrance.py
ponponon-0.1.0.dist-info/METADATA
ponponon-0.1.0.dist-info/WHEEL
ponponon-0.1.0.dist-info/entry_points.txt
ponponon-0.1.0.dist-info/top_level.txt
ponponon-0.1.0.dist-info/RECORD
