Metadata-Version: 2.1
Name: ponponon
Version: 0.1.0
Summary: An advanced message queue framework, derived from nameko
Home-page: https://github.com/ponponon/pon
Author: ponponon
Author-email: 1729303158@qq.com
Maintainer: ponponon
Maintainer-email: 1729303158@qq.com
License: MIT License
Platform: all
Classifier: Programming Language :: Python
Classifier: Operating System :: MacOS :: MacOS X
Classifier: Operating System :: POSIX
Classifier: Programming Language :: Python :: 3
Classifier: Programming Language :: Python :: 3.8
Classifier: Programming Language :: Python :: 3.9
Classifier: Programming Language :: Python :: 3.10
Classifier: Programming Language :: Python :: 3.11
Classifier: Programming Language :: Python :: 3.12
Classifier: Topic :: Internet
Classifier: Topic :: Software Development :: Libraries :: Python Modules
Classifier: Intended Audience :: Developers
Requires-Dist: pydantic
Requires-Dist: loguru
Requires-Dist: pyyaml
Requires-Dist: eventlet
Requires-Dist: kombu
Requires-Dist: werkzeug
